rb_deeplearning_lib/__init__.py
rb_deeplearning_lib/autogradient.py
rb_deeplearning_lib/neural_net.py
rb_deeplearning_lib/sequence.py
rb_deeplearning_lib-0.0.2.dist-info/licenses/LICENSE
rb_deeplearning_lib-0.0.2.dist-info/METADATA
rb_deeplearning_lib-0.0.2.dist-info/WHEEL
rb_deeplearning_lib-0.0.2.dist-info/top_level.txt
rb_deeplearning_lib-0.0.2.dist-info/RECORD
